MANIFEST.in
README.rst
setup.py
blockedemails/__init__.py
blockedemails/admin.py
blockedemails/fields.py
blockedemails/models.py
blockedemails/validators.py
django_blockedemails.egg-info/PKG-INFO
django_blockedemails.egg-info/SOURCES.txt
django_blockedemails.egg-info/dependency_links.txt
django_blockedemails.egg-info/top_level.txt