Metadata-Version: 1.0
Name: django-blockedemails
Version: 0.1.0
Summary: A Django reusable app that provides a form field, models and validators for blocking email addresses
Home-page: http://github.com/dstufft/django-blockedemails/
Author: Donald Stufft
Author-email: donald@e.vilgeni.us
License: BSD
Platform: UNKNOWN
Classifier: Development Status :: 4 - Beta
Classifier: Environment :: Web Environment
Classifier: Intended Audience :: Developers
Classifier: License :: OSI Approved :: BSD License
Classifier: Operating System :: OS Independent
Classifier: Programming Language :: Python
Classifier: Topic :: Utilities
Classifier: Framework :: Django
